socket_asyncio_threaded/__init__.py
socket_asyncio_threaded/client.py
socket_asyncio_threaded-0.0.2.dist-info/LICENSE
socket_asyncio_threaded-0.0.2.dist-info/METADATA
socket_asyncio_threaded-0.0.2.dist-info/WHEEL
socket_asyncio_threaded-0.0.2.dist-info/top_level.txt
socket_asyncio_threaded-0.0.2.dist-info/RECORD
