Metadata-Version: 2.1
Name: socket_asyncio_threaded
Version: 0.0.2
Summary: Send and receive data with asyncio in another single thread
Home-page: https://github.com/S3Studio/socket_asyncio_threaded
Author: S3Studio
Author-email: smallay.sss@gmail.com
License: UNKNOWN
Project-URL: Bug Tracker, https://github.com/S3Studio/socket_asyncio_threaded/issues
Platform: UNKNOWN
Classifier: Programming Language :: Python :: 3
Classifier: License :: OSI Approved :: MIT License
Classifier: Operating System :: OS Independent
Requires-Python: >=3.7
License-File: LICENSE
